[
  {
    "line": 1,
    "elements": [
      {
        "line": 3,
        "name": "",
        "description": "",
        "type": "background",
        "keyword": "Background",
        "steps": [
          {
            "result": {
              "duration": 2427377100,
              "status": "passed"
            },
            "line": 4,
            "name": "click on messages tab",
            "match": {
              "location": "composeMessage.click_on_messages_tab()"
            },
            "keyword": "Given "
          }
        ]
      },
      {
        "start_timestamp": "2022-06-23T09:38:41.552Z",
        "before": [
          {
            "result": {
              "duration": 14877297200,
              "status": "passed"
            },
            "match": {
              "location": "hooksClass.init()"
            }
          }
        ],
        "line": 14,
        "name": "Enter valid information",
        "description": "",
        "id": "compose-message;enter-valid-information;;2",
        "after": [
          {
            "result": {
              "duration": 704442300,
              "status": "passed"
            },
            "match": {
              "location": "hooksClass.quit()"
            }
          }
        ],
        "type": "scenario",
        "keyword": "Scenario Outline",
        "steps": [
          {
            "result": {
              "duration": 2500386900,
              "status": "passed"
            },
            "line": 8,
            "name": "enter valid data username \"Meghna Chakraborty\" and subject\"hello\"",
            "match": {
              "arguments": [
                {
                  "val": "\"Meghna Chakraborty\"",
                  "offset": 26
                },
                {
                  "val": "\"hello\"",
                  "offset": 58
                }
              ],
              "location": "composeMessage.enter_valid_data_username_and_subject(String,String)"
            },
            "keyword": "When "
          },
          {
            "result": {
              "duration": 2593912800,
              "status": "passed"
            },
            "line": 9,
            "name": "click on send message",
            "match": {
              "location": "composeMessage.click_on_send_message()"
            },
            "keyword": "And "
          },
          {
            "result": {
              "duration": 74580400,
              "status": "passed"
            },
            "line": 10,
            "name": "verify the message username \"Meghna Chakraborty\"",
            "match": {
              "arguments": [
                {
                  "val": "\"Meghna Chakraborty\"",
                  "offset": 28
                }
              ],
              "location": "composeMessage.verify_the_message_username(String)"
            },
            "keyword": "Then "
          }
        ],
        "tags": [
          {
            "name": "@valid"
          }
        ]
      },
      {
        "line": 3,
        "name": "",
        "description": "",
        "type": "background",
        "keyword": "Background",
        "steps": [
          {
            "result": {
              "duration": 1687517100,
              "status": "passed"
            },
            "line": 4,
            "name": "click on messages tab",
            "match": {
              "location": "composeMessage.click_on_messages_tab()"
            },
            "keyword": "Given "
          }
        ]
      },
      {
        "start_timestamp": "2022-06-23T09:39:04.736Z",
        "before": [
          {
            "result": {
              "duration": 13612620200,
              "status": "passed"
            },
            "match": {
              "location": "hooksClass.init()"
            }
          }
        ],
        "line": 15,
        "name": "Enter valid information",
        "description": "",
        "id": "compose-message;enter-valid-information;;3",
        "after": [
          {
            "result": {
              "duration": 679507400,
              "status": "passed"
            },
            "match": {
              "location": "hooksClass.quit()"
            }
          }
        ],
        "type": "scenario",
        "keyword": "Scenario Outline",
        "steps": [
          {
            "result": {
              "duration": 2378767500,
              "status": "passed"
            },
            "line": 8,
            "name": "enter valid data username \"Abcd Pqrs\" and subject\"hola\"",
            "match": {
              "arguments": [
                {
                  "val": "\"Abcd Pqrs\"",
                  "offset": 26
                },
                {
                  "val": "\"hola\"",
                  "offset": 49
                }
              ],
              "location": "composeMessage.enter_valid_data_username_and_subject(String,String)"
            },
            "keyword": "When "
          },
          {
            "result": {
              "duration": 1313106200,
              "status": "passed"
            },
            "line": 9,
            "name": "click on send message",
            "match": {
              "location": "composeMessage.click_on_send_message()"
            },
            "keyword": "And "
          },
          {
            "result": {
              "duration": 61163700,
              "status": "passed"
            },
            "line": 10,
            "name": "verify the message username \"Abcd Pqrs\"",
            "match": {
              "arguments": [
                {
                  "val": "\"Abcd Pqrs\"",
                  "offset": 28
                }
              ],
              "location": "composeMessage.verify_the_message_username(String)"
            },
            "keyword": "Then "
          }
        ],
        "tags": [
          {
            "name": "@valid"
          }
        ]
      },
      {
        "line": 3,
        "name": "",
        "description": "",
        "type": "background",
        "keyword": "Background",
        "steps": [
          {
            "result": {
              "duration": 3670150300,
              "status": "passed"
            },
            "line": 4,
            "name": "click on messages tab",
            "match": {
              "location": "composeMessage.click_on_messages_tab()"
            },
            "keyword": "Given "
          }
        ]
      },
      {
        "start_timestamp": "2022-06-23T09:39:24.470Z",
        "before": [
          {
            "result": {
              "duration": 12939794200,
              "status": "passed"
            },
            "match": {
              "location": "hooksClass.init()"
            }
          }
        ],
        "line": 16,
        "name": "Enter valid information",
        "description": "",
        "id": "compose-message;enter-valid-information;;4",
        "after": [
          {
            "result": {
              "duration": 668739100,
              "status": "passed"
            },
            "match": {
              "location": "hooksClass.quit()"
            }
          }
        ],
        "type": "scenario",
        "keyword": "Scenario Outline",
        "steps": [
          {
            "result": {
              "duration": 2446131700,
              "status": "passed"
            },
            "line": 8,
            "name": "enter valid data username \"Anamika Anamika\" and subject\"bonjour\"",
            "match": {
              "arguments": [
                {
                  "val": "\"Anamika Anamika\"",
                  "offset": 26
                },
                {
                  "val": "\"bonjour\"",
                  "offset": 55
                }
              ],
              "location": "composeMessage.enter_valid_data_username_and_subject(String,String)"
            },
            "keyword": "When "
          },
          {
            "result": {
              "duration": 1442912200,
              "status": "passed"
            },
            "line": 9,
            "name": "click on send message",
            "match": {
              "location": "composeMessage.click_on_send_message()"
            },
            "keyword": "And "
          },
          {
            "result": {
              "duration": 58227600,
              "status": "passed"
            },
            "line": 10,
            "name": "verify the message username \"Anamika Anamika\"",
            "match": {
              "arguments": [
                {
                  "val": "\"Anamika Anamika\"",
                  "offset": 28
                }
              ],
              "location": "composeMessage.verify_the_message_username(String)"
            },
            "keyword": "Then "
          }
        ],
        "tags": [
          {
            "name": "@valid"
          }
        ]
      },
      {
        "line": 3,
        "name": "",
        "description": "",
        "type": "background",
        "keyword": "Background",
        "steps": [
          {
            "result": {
              "duration": 1743021600,
              "status": "passed"
            },
            "line": 4,
            "name": "click on messages tab",
            "match": {
              "location": "composeMessage.click_on_messages_tab()"
            },
            "keyword": "Given "
          }
        ]
      },
      {
        "start_timestamp": "2022-06-23T09:39:45.698Z",
        "before": [
          {
            "result": {
              "duration": 13449961600,
              "status": "passed"
            },
            "match": {
              "location": "hooksClass.init()"
            }
          }
        ],
        "line": 26,
        "name": "Enter invalid information",
        "description": "",
        "id": "compose-message;enter-invalid-information;;2",
        "after": [
          {
            "result": {
              "duration": 665628200,
              "status": "passed"
            },
            "match": {
              "location": "hooksClass.quit()"
            }
          }
        ],
        "type": "scenario",
        "keyword": "Scenario Outline",
        "steps": [
          {
            "result": {
              "duration": 149918100,
              "status": "passed"
            },
            "line": 20,
            "name": "enter invalid data username \"\" and subject\"hello\"",
            "match": {
              "arguments": [
                {
                  "val": "\"\"",
                  "offset": 28
                },
                {
                  "val": "\"hello\"",
                  "offset": 42
                }
              ],
              "location": "composeMessage.enter_invalid_data_username_and_subject(String,String)"
            },
            "keyword": "When "
          },
          {
            "result": {
              "duration": 852931500,
              "status": "passed"
            },
            "line": 21,
            "name": "click on send message",
            "match": {
              "location": "composeMessage.click_on_send_message()"
            },
            "keyword": "And "
          },
          {
            "result": {
              "duration": 55276500,
              "status": "passed"
            },
            "line": 22,
            "name": "verify the output message",
            "match": {
              "location": "composeMessage.verify_the_output_message()"
            },
            "keyword": "Then "
          }
        ],
        "tags": [
          {
            "name": "@invalid"
          }
        ]
      },
      {
        "line": 3,
        "name": "",
        "description": "",
        "type": "background",
        "keyword": "Background",
        "steps": [
          {
            "result": {
              "duration": 1717641900,
              "status": "passed"
            },
            "line": 4,
            "name": "click on messages tab",
            "match": {
              "location": "composeMessage.click_on_messages_tab()"
            },
            "keyword": "Given "
          }
        ]
      },
      {
        "start_timestamp": "2022-06-23T09:40:02.616Z",
        "before": [
          {
            "result": {
              "duration": 13097980700,
              "status": "passed"
            },
            "match": {
              "location": "hooksClass.init()"
            }
          }
        ],
        "line": 27,
        "name": "Enter invalid information",
        "description": "",
        "id": "compose-message;enter-invalid-information;;3",
        "after": [
          {
            "result": {
              "duration": 674885900,
              "status": "passed"
            },
            "match": {
              "location": "hooksClass.quit()"
            }
          }
        ],
        "type": "scenario",
        "keyword": "Scenario Outline",
        "steps": [
          {
            "result": {
              "duration": 145939300,
              "status": "passed"
            },
            "line": 20,
            "name": "enter invalid data username \"\" and subject\"hola\"",
            "match": {
              "arguments": [
                {
                  "val": "\"\"",
                  "offset": 28
                },
                {
                  "val": "\"hola\"",
                  "offset": 42
                }
              ],
              "location": "composeMessage.enter_invalid_data_username_and_subject(String,String)"
            },
            "keyword": "When "
          },
          {
            "result": {
              "duration": 960429500,
              "status": "passed"
            },
            "line": 21,
            "name": "click on send message",
            "match": {
              "location": "composeMessage.click_on_send_message()"
            },
            "keyword": "And "
          },
          {
            "result": {
              "duration": 41053100,
              "status": "passed"
            },
            "line": 22,
            "name": "verify the output message",
            "match": {
              "location": "composeMessage.verify_the_output_message()"
            },
            "keyword": "Then "
          }
        ],
        "tags": [
          {
            "name": "@invalid"
          }
        ]
      },
      {
        "line": 3,
        "name": "",
        "description": "",
        "type": "background",
        "keyword": "Background",
        "steps": [
          {
            "result": {
              "duration": 1898468600,
              "status": "passed"
            },
            "line": 4,
            "name": "click on messages tab",
            "match": {
              "location": "composeMessage.click_on_messages_tab()"
            },
            "keyword": "Given "
          }
        ]
      },
      {
        "start_timestamp": "2022-06-23T09:40:19.255Z",
        "before": [
          {
            "result": {
              "duration": 12209069100,
              "status": "passed"
            },
            "match": {
              "location": "hooksClass.init()"
            }
          }
        ],
        "line": 30,
        "name": "Dont enter mandatory field",
        "description": "",
        "id": "compose-message;dont-enter-mandatory-field",
        "after": [
          {
            "result": {
              "duration": 660392400,
              "status": "passed"
            },
            "match": {
              "location": "hooksClass.quit()"
            }
          }
        ],
        "type": "scenario",
        "keyword": "Scenario",
        "steps": [
          {
            "result": {
              "duration": 2270759900,
              "status": "passed"
            },
            "line": 31,
            "name": "enter valid data username",
            "match": {
              "location": "composeMessage.enter_valid_data_username()"
            },
            "keyword": "When "
          },
          {
            "result": {
              "duration": 753886000,
              "status": "passed"
            },
            "line": 32,
            "name": "click on send message",
            "match": {
              "location": "composeMessage.click_on_send_message()"
            },
            "keyword": "And "
          },
          {
            "result": {
              "duration": 50510500,
              "status": "passed"
            },
            "line": 33,
            "name": "verify the error message",
            "match": {
              "location": "composeMessage.verify_the_error_message()"
            },
            "keyword": "Then "
          }
        ],
        "tags": [
          {
            "name": "@mandatory"
          }
        ]
      }
    ],
    "name": "Compose Message",
    "description": "",
    "id": "compose-message",
    "keyword": "Feature",
    "uri": "file:src/test/java/feature/composeMessage.feature",
    "tags": []
  },
  {
    "line": 1,
    "elements": [
      {
        "line": 3,
        "name": "click on outb",
        "description": "",
        "type": "background",
        "keyword": "Background",
        "steps": [
          {
            "result": {
              "duration": 1113404500,
              "status": "passed"
            },
            "line": 4,
            "name": "click on outboxs",
            "match": {
              "location": "composeMessage.click_on_outboxs()"
            },
            "keyword": "Given "
          }
        ]
      },
      {
        "start_timestamp": "2022-06-23T09:40:37.100Z",
        "before": [
          {
            "result": {
              "duration": 13334289600,
              "status": "passed"
            },
            "match": {
              "location": "hooksClass.init()"
            }
          }
        ],
        "line": 7,
        "name": "delete a message",
        "description": "",
        "id": "outbox;delete-a-message",
        "after": [
          {
            "result": {
              "duration": 696725700,
              "status": "passed"
            },
            "match": {
              "location": "hooksClass.quit()"
            }
          }
        ],
        "type": "scenario",
        "keyword": "Scenario",
        "steps": [
          {
            "result": {
              "duration": 114640700,
              "status": "passed"
            },
            "line": 8,
            "name": "click on delete message",
            "match": {
              "location": "composeMessage.click_on_delete_message()"
            },
            "keyword": "When "
          },
          {
            "result": {
              "duration": 16124800,
              "status": "passed"
            },
            "line": 9,
            "name": "select the alert",
            "match": {
              "location": "composeMessage.select_the_alert()"
            },
            "keyword": "And "
          },
          {
            "result": {
              "duration": 1140139600,
              "status": "passed"
            },
            "line": 10,
            "name": "check for validation message",
            "match": {
              "location": "composeMessage.check_for_validation_message()"
            },
            "keyword": "Then "
          }
        ],
        "tags": [
          {
            "name": "@delete"
          }
        ]
      },
      {
        "line": 3,
        "name": "click on outb",
        "description": "",
        "type": "background",
        "keyword": "Background",
        "steps": [
          {
            "result": {
              "duration": 1134166100,
              "status": "passed"
            },
            "line": 4,
            "name": "click on outboxs",
            "match": {
              "location": "composeMessage.click_on_outboxs()"
            },
            "keyword": "Given "
          }
        ]
      },
      {
        "start_timestamp": "2022-06-23T09:40:53.517Z",
        "before": [
          {
            "result": {
              "duration": 15067310500,
              "status": "passed"
            },
            "match": {
              "location": "hooksClass.init()"
            }
          }
        ],
        "line": 13,
        "name": "select some messages",
        "description": "",
        "id": "outbox;select-some-messages",
        "after": [
          {
            "result": {
              "duration": 1414491300,
              "status": "passed"
            },
            "match": {
              "location": "hooksClass.quit()"
            }
          }
        ],
        "type": "scenario",
        "keyword": "Scenario",
        "steps": [
          {
            "result": {
              "duration": 3113243000,
              "status": "passed"
            },
            "line": 14,
            "name": "select any given message",
            "match": {
              "location": "composeMessage.select_any_given_message()"
            },
            "keyword": "When "
          },
          {
            "result": {
              "duration": 20944100,
              "status": "passed"
            },
            "line": 15,
            "name": "check if the message is selected",
            "match": {
              "location": "composeMessage.check_if_the_message_is_selected()"
            },
            "keyword": "Then "
          }
        ],
        "tags": [
          {
            "name": "@select"
          }
        ]
      },
      {
        "line": 3,
        "name": "click on outb",
        "description": "",
        "type": "background",
        "keyword": "Background",
        "steps": [
          {
            "result": {
              "duration": 1056463600,
              "status": "passed"
            },
            "line": 4,
            "name": "click on outboxs",
            "match": {
              "location": "composeMessage.click_on_outboxs()"
            },
            "keyword": "Given "
          }
        ]
      },
      {
        "start_timestamp": "2022-06-23T09:41:14.268Z",
        "before": [
          {
            "result": {
              "duration": 13967084000,
              "status": "passed"
            },
            "match": {
              "location": "hooksClass.init()"
            }
          }
        ],
        "line": 24,
        "name": "open a message",
        "description": "",
        "id": "outbox;open-a-message;;2",
        "after": [
          {
            "result": {
              "duration": 662845900,
              "status": "passed"
            },
            "match": {
              "location": "hooksClass.quit()"
            }
          }
        ],
        "type": "scenario",
        "keyword": "Scenario Outline",
        "steps": [
          {
            "result": {
              "duration": 2949825500,
              "status": "passed"
            },
            "line": 19,
            "name": "open a message using title title \"hello\"",
            "match": {
              "arguments": [
                {
                  "val": "\"hello\"",
                  "offset": 33
                }
              ],
              "location": "composeMessage.open_a_message_using_title_title(String)"
            },
            "keyword": "When "
          },
          {
            "result": {
              "duration": 34823800,
              "status": "passed"
            },
            "line": 20,
            "name": "check if message is opened",
            "match": {
              "location": "composeMessage.check_if_message_is_opened()"
            },
            "keyword": "Then "
          }
        ],
        "tags": [
          {
            "name": "@open"
          }
        ]
      },
      {
        "line": 3,
        "name": "click on outb",
        "description": "",
        "type": "background",
        "keyword": "Background",
        "steps": [
          {
            "result": {
              "duration": 1032254400,
              "status": "passed"
            },
            "line": 4,
            "name": "click on outboxs",
            "match": {
              "location": "composeMessage.click_on_outboxs()"
            },
            "keyword": "Given "
          }
        ]
      },
      {
        "start_timestamp": "2022-06-23T09:41:32.940Z",
        "before": [
          {
            "result": {
              "duration": 13230941700,
              "status": "passed"
            },
            "match": {
              "location": "hooksClass.init()"
            }
          }
        ],
        "line": 25,
        "name": "open a message",
        "description": "",
        "id": "outbox;open-a-message;;3",
        "after": [
          {
            "result": {
              "duration": 661512600,
              "status": "passed"
            },
            "match": {
              "location": "hooksClass.quit()"
            }
          }
        ],
        "type": "scenario",
        "keyword": "Scenario Outline",
        "steps": [
          {
            "result": {
              "duration": 2931042700,
              "status": "passed"
            },
            "line": 19,
            "name": "open a message using title title \"hola\"",
            "match": {
              "arguments": [
                {
                  "val": "\"hola\"",
                  "offset": 33
                }
              ],
              "location": "composeMessage.open_a_message_using_title_title(String)"
            },
            "keyword": "When "
          },
          {
            "result": {
              "duration": 37556700,
              "status": "passed"
            },
            "line": 20,
            "name": "check if message is opened",
            "match": {
              "location": "composeMessage.check_if_message_is_opened()"
            },
            "keyword": "Then "
          }
        ],
        "tags": [
          {
            "name": "@open"
          }
        ]
      },
      {
        "line": 3,
        "name": "click on outb",
        "description": "",
        "type": "background",
        "keyword": "Background",
        "steps": [
          {
            "result": {
              "duration": 1983688900,
              "status": "passed"
            },
            "line": 4,
            "name": "click on outboxs",
            "match": {
              "location": "composeMessage.click_on_outboxs()"
            },
            "keyword": "Given "
          }
        ]
      },
      {
        "start_timestamp": "2022-06-23T09:41:50.835Z",
        "before": [
          {
            "result": {
              "duration": 14699596700,
              "status": "passed"
            },
            "match": {
              "location": "hooksClass.init()"
            }
          }
        ],
        "line": 26,
        "name": "open a message",
        "description": "",
        "id": "outbox;open-a-message;;4",
        "after": [
          {
            "result": {
              "duration": 682589100,
              "status": "passed"
            },
            "match": {
              "location": "hooksClass.quit()"
            }
          }
        ],
        "type": "scenario",
        "keyword": "Scenario Outline",
        "steps": [
          {
            "result": {
              "duration": 2979095900,
              "status": "passed"
            },
            "line": 19,
            "name": "open a message using title title \"bonjour\"",
            "match": {
              "arguments": [
                {
                  "val": "\"bonjour\"",
                  "offset": 33
                }
              ],
              "location": "composeMessage.open_a_message_using_title_title(String)"
            },
            "keyword": "When "
          },
          {
            "result": {
              "duration": 48591000,
              "status": "passed"
            },
            "line": 20,
            "name": "check if message is opened",
            "match": {
              "location": "composeMessage.check_if_message_is_opened()"
            },
            "keyword": "Then "
          }
        ],
        "tags": [
          {
            "name": "@open"
          }
        ]
      }
    ],
    "name": "outbox",
    "description": "",
    "id": "outbox",
    "keyword": "Feature",
    "uri": "file:src/test/java/feature/outbox.feature",
    "tags": []
  },
  {
    "line": 1,
    "elements": [
      {
        "line": 3,
        "name": "click on outb",
        "description": "",
        "type": "background",
        "keyword": "Background",
        "steps": [
          {
            "result": {
              "duration": 1040201400,
              "status": "passed"
            },
            "line": 4,
            "name": "click on outboxs",
            "match": {
              "location": "composeMessage.click_on_outboxs()"
            },
            "keyword": "Given "
          }
        ]
      },
      {
        "start_timestamp": "2022-06-23T09:42:11.229Z",
        "before": [
          {
            "result": {
              "duration": 13949990800,
              "status": "passed"
            },
            "match": {
              "location": "hooksClass.init()"
            }
          }
        ],
        "line": 14,
        "name": "enter in valid search data",
        "description": "",
        "id": "search;enter-in-valid-search-data;;2",
        "after": [
          {
            "result": {
              "duration": 649093700,
              "status": "passed"
            },
            "match": {
              "location": "hooksClass.quit()"
            }
          }
        ],
        "type": "scenario",
        "keyword": "Scenario Outline",
        "steps": [
          {
            "result": {
              "duration": 134169000,
              "status": "passed"
            },
            "line": 8,
            "name": "click on search and enter values value \"hello\"",
            "match": {
              "arguments": [
                {
                  "val": "\"hello\"",
                  "offset": 39
                }
              ],
              "location": "composeMessage.click_on_search_and_enter_values_value(String)"
            },
            "keyword": "When "
          },
          {
            "result": {
              "duration": 1136454300,
              "status": "passed"
            },
            "line": 9,
            "name": "click on search button",
            "match": {
              "location": "composeMessage.click_on_search_button()"
            },
            "keyword": "When "
          },
          {
            "result": {
              "duration": 42198600,
              "status": "passed"
            },
            "line": 10,
            "name": "check if message are avilable value\"hello\"",
            "match": {
              "arguments": [
                {
                  "val": "\"hello\"",
                  "offset": 35
                }
              ],
              "location": "composeMessage.check_if_message_are_avilable_value(String)"
            },
            "keyword": "Then "
          }
        ],
        "tags": [
          {
            "name": "@search"
          }
        ]
      },
      {
        "line": 3,
        "name": "click on outb",
        "description": "",
        "type": "background",
        "keyword": "Background",
        "steps": [
          {
            "result": {
              "duration": 1081042000,
              "status": "passed"
            },
            "line": 4,
            "name": "click on outboxs",
            "match": {
              "location": "composeMessage.click_on_outboxs()"
            },
            "keyword": "Given "
          }
        ]
      },
      {
        "start_timestamp": "2022-06-23T09:42:28.183Z",
        "before": [
          {
            "result": {
              "duration": 14784699300,
              "status": "passed"
            },
            "match": {
              "location": "hooksClass.init()"
            }
          }
        ],
        "line": 15,
        "name": "enter in valid search data",
        "description": "",
        "id": "search;enter-in-valid-search-data;;3",
        "after": [
          {
            "result": {
              "duration": 662975100,
              "status": "passed"
            },
            "match": {
              "location": "hooksClass.quit()"
            }
          }
        ],
        "type": "scenario",
        "keyword": "Scenario Outline",
        "steps": [
          {
            "result": {
              "duration": 126446300,
              "status": "passed"
            },
            "line": 8,
            "name": "click on search and enter values value \"hola\"",
            "match": {
              "arguments": [
                {
                  "val": "\"hola\"",
                  "offset": 39
                }
              ],
              "location": "composeMessage.click_on_search_and_enter_values_value(String)"
            },
            "keyword": "When "
          },
          {
            "result": {
              "duration": 856284800,
              "status": "passed"
            },
            "line": 9,
            "name": "click on search button",
            "match": {
              "location": "composeMessage.click_on_search_button()"
            },
            "keyword": "When "
          },
          {
            "result": {
              "duration": 55624600,
              "status": "passed"
            },
            "line": 10,
            "name": "check if message are avilable value\"hola\"",
            "match": {
              "arguments": [
                {
                  "val": "\"hola\"",
                  "offset": 35
                }
              ],
              "location": "composeMessage.check_if_message_are_avilable_value(String)"
            },
            "keyword": "Then "
          }
        ],
        "tags": [
          {
            "name": "@search"
          }
        ]
      },
      {
        "line": 3,
        "name": "click on outb",
        "description": "",
        "type": "background",
        "keyword": "Background",
        "steps": [
          {
            "result": {
              "duration": 1028378700,
              "status": "passed"
            },
            "line": 4,
            "name": "click on outboxs",
            "match": {
              "location": "composeMessage.click_on_outboxs()"
            },
            "keyword": "Given "
          }
        ]
      },
      {
        "start_timestamp": "2022-06-23T09:42:45.751Z",
        "before": [
          {
            "result": {
              "duration": 13572672600,
              "status": "passed"
            },
            "match": {
              "location": "hooksClass.init()"
            }
          }
        ],
        "line": 16,
        "name": "enter in valid search data",
        "description": "",
        "id": "search;enter-in-valid-search-data;;4",
        "after": [
          {
            "result": {
              "duration": 655136500,
              "status": "passed"
            },
            "match": {
              "location": "hooksClass.quit()"
            }
          }
        ],
        "type": "scenario",
        "keyword": "Scenario Outline",
        "steps": [
          {
            "result": {
              "duration": 116729900,
              "status": "passed"
            },
            "line": 8,
            "name": "click on search and enter values value \"bonjour\"",
            "match": {
              "arguments": [
                {
                  "val": "\"bonjour\"",
                  "offset": 39
                }
              ],
              "location": "composeMessage.click_on_search_and_enter_values_value(String)"
            },
            "keyword": "When "
          },
          {
            "result": {
              "duration": 844070900,
              "status": "passed"
            },
            "line": 9,
            "name": "click on search button",
            "match": {
              "location": "composeMessage.click_on_search_button()"
            },
            "keyword": "When "
          },
          {
            "result": {
              "duration": 50668500,
              "status": "passed"
            },
            "line": 10,
            "name": "check if message are avilable value\"bonjour\"",
            "match": {
              "arguments": [
                {
                  "val": "\"bonjour\"",
                  "offset": 35
                }
              ],
              "location": "composeMessage.check_if_message_are_avilable_value(String)"
            },
            "keyword": "Then "
          }
        ],
        "tags": [
          {
            "name": "@search"
          }
        ]
      },
      {
        "line": 3,
        "name": "click on outb",
        "description": "",
        "type": "background",
        "keyword": "Background",
        "steps": [
          {
            "result": {
              "duration": 1087670800,
              "status": "passed"
            },
            "line": 4,
            "name": "click on outboxs",
            "match": {
              "location": "composeMessage.click_on_outboxs()"
            },
            "keyword": "Given "
          }
        ]
      },
      {
        "start_timestamp": "2022-06-23T09:43:02.020Z",
        "before": [
          {
            "result": {
              "duration": 13486125900,
              "status": "passed"
            },
            "match": {
              "location": "hooksClass.init()"
            }
          }
        ],
        "line": 17,
        "name": "enter in valid search data",
        "description": "",
        "id": "search;enter-in-valid-search-data;;5",
        "after": [
          {
            "result": {
              "duration": 715264100,
              "status": "passed"
            },
            "match": {
              "location": "hooksClass.quit()"
            }
          }
        ],
        "type": "scenario",
        "keyword": "Scenario Outline",
        "steps": [
          {
            "result": {
              "duration": 159185400,
              "status": "passed"
            },
            "line": 8,
            "name": "click on search and enter values value \"Meghna Chakraborty\"",
            "match": {
              "arguments": [
                {
                  "val": "\"Meghna Chakraborty\"",
                  "offset": 39
                }
              ],
              "location": "composeMessage.click_on_search_and_enter_values_value(String)"
            },
            "keyword": "When "
          },
          {
            "result": {
              "duration": 790387100,
              "status": "passed"
            },
            "line": 9,
            "name": "click on search button",
            "match": {
              "location": "composeMessage.click_on_search_button()"
            },
            "keyword": "When "
          },
          {
            "result": {
              "error_message": "org.openqa.selenium.NoSuchElementException: no such element: Unable to locate element: {\"method\":\"xpath\",\"selector\":\"//div//tbody//tr//td[2]//a[text()\u003d\u0027Meghna Chakraborty\u0027]\"}\n  (Session info: chrome\u003d102.0.5005.115)\nFor documentation on this error, please visit: https://www.seleniumhq.org/exceptions/no_such_element.html\nBuild info: version: \u00273.141.59\u0027, revision: \u0027e82be7d358\u0027, time: \u00272018-11-14T08:17:03\u0027\nSystem info: host: \u0027WIN-JO8IQI19CKC\u0027, ip: \u0027192.168.1.195\u0027, os.name: \u0027Windows 10\u0027, os.arch: \u0027amd64\u0027, os.version: \u002710.0\u0027, java.version: \u00271.8.0_202\u0027\nDriver info: org.openqa.selenium.chrome.ChromeDriver\nCapabilities {acceptInsecureCerts: false, browserName: chrome, browserVersion: 102.0.5005.115, chrome: {chromedriverVersion: 102.0.5005.61 (0e59bcc00cc4..., userDataDir: C:\\Users\\003QUT~1\\AppData\\L...}, goog:chromeOptions: {debuggerAddress: localhost:56202}, javascriptEnabled: true, networkConnectionEnabled: false, pageLoadStrategy: normal, platform: WINDOWS, platformName: WINDOWS, proxy: Proxy(), setWindowRect: true, strictFileInteractability: false, timeouts: {implicit: 0, pageLoad: 300000, script: 30000}, unhandledPromptBehavior: dismiss and notify, webauthn:extension:credBlob: true, webauthn:extension:largeBlob: true, webauthn:virtualAuthenticators: true}\nSession ID: 7de0b84a76eb42c3c049a5b650647785\n*** Element info: {Using\u003dxpath, value\u003d//div//tbody//tr//td[2]//a[text()\u003d\u0027Meghna Chakraborty\u0027]}\r\n\tat sun.reflect.NativeConstructorAccessorImpl.newInstance0(Native Method)\r\n\tat sun.reflect.NativeConstructorAccessorImpl.newInstance(Unknown Source)\r\n\tat sun.reflect.DelegatingConstructorAccessorImpl.newInstance(Unknown Source)\r\n\tat java.lang.reflect.Constructor.newInstance(Unknown Source)\r\n\tat org.openqa.selenium.remote.http.W3CHttpResponseCodec.createException(W3CHttpResponseCodec.java:187)\r\n\tat org.openqa.selenium.remote.http.W3CHttpResponseCodec.decode(W3CHttpResponseCodec.java:122)\r\n\tat org.openqa.selenium.remote.http.W3CHttpResponseCodec.decode(W3CHttpResponseCodec.java:49)\r\n\tat org.openqa.selenium.remote.HttpCommandExecutor.execute(HttpCommandExecutor.java:158)\r\n\tat org.openqa.selenium.remote.service.DriverCommandExecutor.execute(DriverCommandExecutor.java:83)\r\n\tat org.openqa.selenium.remote.RemoteWebDriver.execute(RemoteWebDriver.java:552)\r\n\tat org.openqa.selenium.remote.RemoteWebDriver.findElement(RemoteWebDriver.java:323)\r\n\tat org.openqa.selenium.remote.RemoteWebDriver.findElementByXPath(RemoteWebDriver.java:428)\r\n\tat org.openqa.selenium.By$ByXPath.findElement(By.java:353)\r\n\tat org.openqa.selenium.remote.RemoteWebDriver.findElement(RemoteWebDriver.java:315)\r\n\tat stepdefinition.composeMessage.check_if_message_are_avilable_value(composeMessage.java:181)\r\n\tat ✽.check if message are avilable value\"Meghna Chakraborty\"(file:src/test/java/feature/searchs.feature:10)\r\n",
              "duration": 65276900,
              "status": "failed"
            },
            "line": 10,
            "name": "check if message are avilable value\"Meghna Chakraborty\"",
            "match": {
              "arguments": [
                {
                  "val": "\"Meghna Chakraborty\"",
                  "offset": 35
                }
              ],
              "location": "composeMessage.check_if_message_are_avilable_value(String)"
            },
            "keyword": "Then "
          }
        ],
        "tags": [
          {
            "name": "@search"
          }
        ]
      }
    ],
    "name": "Search",
    "description": "",
    "id": "search",
    "keyword": "Feature",
    "uri": "file:src/test/java/feature/searchs.feature",
    "tags": []
  }
]